weavops/__init__.py
weavops/env.py
weavops/mcp.py
weavops/py.typed
weavops-0.0.2.dist-info/WHEEL
weavops-0.0.2.dist-info/entry_points.txt
weavops-0.0.2.dist-info/METADATA
weavops-0.0.2.dist-info/RECORD
