Metadata-Version: 2.3
Name: weavops
Version: 0.0.2
Summary: WeavOps bridges GitOps with MCP-powered AI agents, automatically weaving your Git source of truth into autonomous, context-aware operations
Author: Yan-Ke Guo
Author-email: Yan-Ke Guo <hi@gyk.me>
License: MIT
Classifier: Development Status :: 3 - Alpha
Classifier: Intended Audience :: Developers
Classifier: Intended Audience :: System Administrators
Classifier: License :: OSI Approved :: MIT License
Classifier: Programming Language :: Python :: 3
Classifier: Programming Language :: Python :: 3.13
Classifier: Topic :: Scientific/Engineering :: Artificial Intelligence
Classifier: Topic :: Software Development :: Libraries :: Python Modules
Classifier: Topic :: Software Development :: Version Control :: Git
Classifier: Topic :: System :: Systems Administration
Requires-Dist: fastmcp>=2.14.0
Requires-Python: >=3.13
Project-URL: Homepage, https://github.com/yankeguo/weavops
Project-URL: Issues, https://github.com/yankeguo/weavops/issues
Project-URL: Repository, https://github.com/yankeguo/weavops
